paddleformers/__init__.py
paddleformers/cli/__init__.py
paddleformers/cli/cli.py
paddleformers/cli/launcher.py
paddleformers/cli/export/__init__.py
paddleformers/cli/export/export.py
paddleformers/cli/hparams/__init__.py
paddleformers/cli/hparams/data_args.py
paddleformers/cli/hparams/export_args.py
paddleformers/cli/hparams/finetuning_args.py
paddleformers/cli/hparams/generating_args.py
paddleformers/cli/hparams/model_args.py
paddleformers/cli/hparams/parser.py
paddleformers/cli/hparams/preprocess_args.py
paddleformers/cli/hparams/server_args.py
paddleformers/cli/train/__init__.py
paddleformers/cli/train/tuner.py
paddleformers/cli/train/auto_parallel/__init__.py
paddleformers/cli/train/auto_parallel/workflow.py
paddleformers/cli/train/deepseek_v3_pretrain/__init__.py
paddleformers/cli/train/deepseek_v3_pretrain/configuration.py
paddleformers/cli/train/deepseek_v3_pretrain/fp8_linear.py
paddleformers/cli/train/deepseek_v3_pretrain/kernel.py
paddleformers/cli/train/deepseek_v3_pretrain/modeling.py
paddleformers/cli/train/deepseek_v3_pretrain/modeling_pp.py
paddleformers/cli/train/deepseek_v3_pretrain/moe_gate.py
paddleformers/cli/train/deepseek_v3_pretrain/moe_layer.py
paddleformers/cli/train/deepseek_v3_pretrain/moe_utils.py
paddleformers/cli/train/deepseek_v3_pretrain/token_dispatcher.py
paddleformers/cli/train/deepseek_v3_pretrain/workflow.py
paddleformers/cli/train/deepseek_v3_pretrain/utils/__init__.py
paddleformers/cli/train/deepseek_v3_pretrain/utils/convert_ckpt_to_sft.py
paddleformers/cli/train/deepseek_v3_pretrain/utils/load_hf_ckpt.py
paddleformers/cli/train/dpo/__init__.py
paddleformers/cli/train/dpo/data_config.py
paddleformers/cli/train/dpo/dpo_argument.py
paddleformers/cli/train/dpo/dpo_estimate_training.py
paddleformers/cli/train/dpo/dpo_trainer.py
paddleformers/cli/train/dpo/workflow.py
paddleformers/cli/train/ernie_pretrain/__init__.py
paddleformers/cli/train/ernie_pretrain/model_config.py
paddleformers/cli/train/ernie_pretrain/workflow.py
paddleformers-1.0.0.dist-info/licenses/LICENSE
paddleformers-1.0.0.dist-info/METADATA
paddleformers-1.0.0.dist-info/WHEEL
paddleformers-1.0.0.dist-info/entry_points.txt
paddleformers-1.0.0.dist-info/top_level.txt
paddleformers-1.0.0.dist-info/RECORD
