Metadata-Version: 2.4
Name: paddleformers
Version: 1.0.0
Summary: Easy-to-use and powerful NLP library with Awesome model zoo, supporting wide-range of NLP tasks from research to industrial applications, including Neural Search, Question Answering, Information Extraction and Sentiment Analysis end-to-end system.
Home-page: https://github.com/PaddlePaddle/PaddleFormers
Author: PaddleFormers Team
Author-email: paddleformers@baidu.com
License: Apache 2.0
Classifier: Programming Language :: Python :: 3
Classifier: Programming Language :: Python :: 3.8
Classifier: Programming Language :: Python :: 3.9
Classifier: Programming Language :: Python :: 3.10
Classifier: License :: OSI Approved :: Apache Software License
Classifier: Operating System :: OS Independent
Requires-Python: >=3.8
License-File: LICENSE
Requires-Dist: colorlog
Requires-Dist: scikit-learn
Requires-Dist: multiprocess
Requires-Dist: datasets>=3.0.0
Requires-Dist: tqdm
Requires-Dist: sentencepiece
Requires-Dist: huggingface_hub>=0.19.2
Requires-Dist: protobuf>=3.20.2
Requires-Dist: visualdl
Requires-Dist: safetensors
Requires-Dist: decord
Requires-Dist: paddlecodec; sys_platform == "linux"
Requires-Dist: fast_dataindex>=0.1.1; platform_system == "Linux"
Requires-Dist: aistudio-sdk>=0.3.0
Requires-Dist: jinja2
Requires-Dist: regex
Requires-Dist: numpy
Requires-Dist: tiktoken
Requires-Dist: ml_dtypes
Requires-Dist: omegaconf
Requires-Dist: modelscope
Requires-Dist: transformers>=4.55.1
Requires-Dist: GPUtil
Requires-Dist: importlib_metadata
Provides-Extra: paddlefleet
Requires-Dist: paddlefleet==0.1.0; extra == "paddlefleet"
Dynamic: author
Dynamic: author-email
Dynamic: classifier
Dynamic: description
Dynamic: description-content-type
Dynamic: home-page
Dynamic: license
Dynamic: license-file
Dynamic: provides-extra
Dynamic: requires-dist
Dynamic: requires-python
Dynamic: summary
